{
	"units": [
		{
			"id": 39,
			"group": "Время",
			"name": "Секунды",
			"short": "сек",
			"k": 1,
			"material": 0
		},
		{
			"id": 38,
			"group": "Время",
			"name": "Минуты",
			"short": "мин",
			"k": 60,
			"material": 0
		},
		{
			"id": 34,
			"group": "Время",
			"name": "Часы",
			"short": "ч",
			"k": 3600,
			"material": 0
		},
		{
			"id": 35,
			"group": "Время",
			"name": "Сутки",
			"short": "сут",
			"k": 86400,
			"material": 0
		},
		{
			"id": 36,
			"group": "Время",
			"name": "Недели",
			"short": "нед",
			"k": 604800,
			"material": 0
		},
		{
			"id": 37,
			"group": "Время",
			"name": "Месяцы",
			"short": "мес",
			"k": 2592000,
			"material": 0
		},
		{
			"id": 40,
			"group": "Электроэнергия",
			"name": "Киловатт-часы",
			"short": "кВт-ч",
			"k": 1,
			"material": 0
		},
		{
			"id": 41,
			"group": "Электроэнергия",
			"name": "Мегаватт-часы",
			"short": "мВт-ч",
			"k": 1000,
			"material": 0
		},
		{
			"id": 42,
			"group": "Электроэнергия",
			"name": "Килокалории",
			"short": "ккал",
			"k": 0.001163,
			"material": 0
		},
		{
			"id": 43,
			"group": "Электроэнергия",
			"name": "Килоджоули",
			"short": "кДж",
			"k": 0.00027778,
			"material": 0
		},
		{
			"id": 1,
			"group": "Количество",
			"name": "Штуки",
			"short": "шт",
			"k": 1,
			"material": 1
		},
		{
			"id": 44,
			"group": "Количество",
			"name": "Упаковка",
			"short": "упак",
			"k": 1,
			"material": 1
		},
		{
			"id": 45,
			"group": "Количество",
			"name": "Комплект",
			"short": "компл",
			"k": 1,
			"material": 1
		},
		{
			"id": 2,
			"group": "Вес",
			"name": "Килограммы",
			"short": "кг",
			"k": 1000,
			"material": 1
		},
		{
			"id": 3,
			"group": "Вес",
			"name": "Граммы",
			"short": "г",
			"k": 1,
			"material": 1
		},
		{
			"id": 4,
			"group": "Вес",
			"name": "Миллиграммы",
			"short": "мг",
			"k": 0.001,
			"material": 1
		},
		{
			"id": 5,
			"group": "Вес",
			"name": "Цeнтнepы",
			"short": "ц",
			"k": 100000,
			"material": 1
		},
		{
			"id": 6,
			"group": "Вес",
			"name": "Тонны",
			"short": "т",
			"k": 1000000,
			"material": 1
		},
		{
			"id": 7,
			"group": "Вес",
			"name": "Фунты",
			"short": "lbs",
			"k": 453.59237,
			"material": 1
		},
		{
			"id": 8,
			"group": "Вес",
			"name": "Унции",
			"short": "oz",
			"k": 28.34952,
			"material": 1
		},
		{
			"id": 9,
			"group": "Вес",
			"name": "Караты",
			"short": "кар",
			"k": 0.2,
			"material": 1
		},
		{
			"id": 10,
			"group": "Объем",
			"name": "Литры",
			"short": "л",
			"k": 1,
			"material": 1
		},
		{
			"id": 11,
			"group": "Объем",
			"name": "Миллилитры",
			"short": "мл",
			"k": 0.001,
			"material": 1
		},
		{
			"id": 12,
			"group": "Объем",
			"name": "Декалитры",
			"short": "дал",
			"k": 10,
			"material": 1
		},
		{
			"id": 16,
			"group": "Объем",
			"name": "Микролитры",
			"short": "мкл",
			"k": {
				"source": "1.0e-6",
				"parsedValue": 0.000001
			},
			"material": 1
		},
		{
			"id": 27,
			"group": "Объем",
			"name": "Куб. метры",
			"short": "куб. м",
			"k": 1000,
			"material": 1
		},
		{
			"id": 28,
			"group": "Объем",
			"name": "Куб. сантиметры",
			"short": "куб. см",
			"k": 0.001,
			"material": 1
		},
		{
			"id": 29,
			"group": "Объем",
			"name": "Куб. дециметры",
			"short": "куб. дм",
			"k": 1,
			"material": 1
		},
		{
			"id": 17,
			"group": "Объем",
			"name": "Жидкие унции",
			"short": "fl oz",
			"k": 0.029573531,
			"material": 1
		},
		{
			"id": 18,
			"group": "Объем",
			"name": "Галлоны",
			"short": "gal",
			"k": 3.785411,
			"material": 1
		},
		{
			"id": 46,
			"group": "Объем",
			"name": "Куб. футы",
			"short": "cu ft",
			"k": 28.3168,
			"material": 1
		},
		{
			"id": 47,
			"group": "Объем",
			"name": "Куб. ярды",
			"short": "cu yd",
			"k": 764.554858,
			"material": 1
		},
		{
			"id": 19,
			"group": "Длина",
			"name": "Метры",
			"short": "м",
			"k": 1,
			"material": 1
		},
		{
			"id": 20,
			"group": "Длина",
			"name": "Сантиметры",
			"short": "см",
			"k": 0.01,
			"material": 1
		},
		{
			"id": 21,
			"group": "Длина",
			"name": "Миллиметры",
			"short": "мм",
			"k": 0.001,
			"material": 1
		},
		{
			"id": 22,
			"group": "Длина",
			"name": "Километры",
			"short": "км",
			"k": 1000,
			"material": 1
		},
		{
			"id": 23,
			"group": "Длина",
			"name": "Дециметры",
			"short": "дм",
			"k": 0.1,
			"material": 1
		},
		{
			"id": 30,
			"group": "Длина",
			"name": "Погонные метры",
			"short": "пог. м",
			"k": 1,
			"material": 1
		},
		{
			"id": 24,
			"group": "Длина",
			"name": "Мили",
			"short": "mi",
			"k": 1609.344,
			"material": 1
		},
		{
			"id": 25,
			"group": "Длина",
			"name": "Футы",
			"short": "ft",
			"k": 0.3048,
			"material": 1
		},
		{
			"id": 26,
			"group": "Длина",
			"name": "Дюймы",
			"short": "in",
			"k": 0.0254,
			"material": 1
		},
		{
			"id": 31,
			"group": "Площадь",
			"name": "Кв. метры",
			"short": "кв. м",
			"k": 1,
			"material": 1
		},
		{
			"id": 32,
			"group": "Площадь",
			"name": "Кв. сантиметры",
			"short": "кв. см",
			"k": 0.0001,
			"material": 1
		},
		{
			"id": 33,
			"group": "Площадь",
			"name": "Кв. дециметры",
			"short": "кв. дм",
			"k": 0.01,
			"material": 1
		},
		{
			"id": 48,
			"group": "Площадь",
			"name": "Кв. футы",
			"short": "sq ft",
			"k": 0.09290304,
			"material": 1
		}
	]
}